NianlideMimiVol3/README.md
NianlideMimiVol3/__init__.py
NianlideMimiVol3/__main__.py
NianlideMimiVol3/file.epub
NianlideMimiVol3/index.html
NianlideMimiVol3/css/__init__.py
NianlideMimiVol3/css/annotations.css
NianlideMimiVol3/css/main.css
NianlideMimiVol3/css/normalize.css
NianlideMimiVol3/css/popup.css
NianlideMimiVol3/font/__init__.py
NianlideMimiVol3/font/fontello.eot
NianlideMimiVol3/font/fontello.svg
NianlideMimiVol3/font/fontello.ttf
NianlideMimiVol3/font/fontello.woff
NianlideMimiVol3/img/__init__.py
NianlideMimiVol3/img/annotator-glyph-sprite.png
NianlideMimiVol3/img/annotator-icon-sprite.png
NianlideMimiVol3/img/apple-touch-icon.png
NianlideMimiVol3/img/cancelfullscreen.png
NianlideMimiVol3/img/close.png
NianlideMimiVol3/img/fullscreen.png
NianlideMimiVol3/img/loader.gif
NianlideMimiVol3/img/menu-icon.png
NianlideMimiVol3/img/save.png
NianlideMimiVol3/img/saved.png
NianlideMimiVol3/img/settings-s.png
NianlideMimiVol3/img/settings.png
NianlideMimiVol3/img/star.png
NianlideMimiVol3/js/__init__.py
NianlideMimiVol3/js/epub.js
NianlideMimiVol3/js/epub.min.js
NianlideMimiVol3/js/epub.min.map
NianlideMimiVol3/js/hooks.min.js
NianlideMimiVol3/js/hooks.min.map
NianlideMimiVol3/js/reader.js
NianlideMimiVol3/js/reader.js.map
NianlideMimiVol3/js/reader.min.js
NianlideMimiVol3/js/reader.min.map
NianlideMimiVol3/js/hooks/__init__.py
NianlideMimiVol3/js/hooks/extensions/__init__.py
NianlideMimiVol3/js/hooks/extensions/highlight.js
NianlideMimiVol3/js/libs/__init__.py
NianlideMimiVol3/js/libs/jquery.min.js
NianlideMimiVol3/js/libs/localforage.min.js
NianlideMimiVol3/js/libs/screenfull.js
NianlideMimiVol3/js/libs/screenfull.min.js
NianlideMimiVol3/js/libs/zip.min.js
NianlideMimiVol3/js/plugins/__init__.py
NianlideMimiVol3/js/plugins/hypothesis.js
NianlideMimiVol3/js/plugins/search.js
nianlide_mimi_vol3-2022.10.14.0.dist-info/METADATA
nianlide_mimi_vol3-2022.10.14.0.dist-info/WHEEL
nianlide_mimi_vol3-2022.10.14.0.dist-info/entry_points.txt
nianlide_mimi_vol3-2022.10.14.0.dist-info/top_level.txt
nianlide_mimi_vol3-2022.10.14.0.dist-info/RECORD
